LICENSE
README.md
setup.py
redditflow/__init__.py
redditflow.egg-info/PKG-INFO
redditflow.egg-info/SOURCES.txt
redditflow.egg-info/dependency_links.txt
redditflow.egg-info/requires.txt
redditflow.egg-info/top_level.txt
redditflow/apis/__init__.py
redditflow/apis/image/ImageApi.py
redditflow/apis/image/__init__.py
redditflow/apis/image/img_utils.py
redditflow/apis/text/TextApi.py
redditflow/apis/text/__init__.py
redditflow/apis/text/txt_utils.py
redditflow/image_search/__init__.py
redditflow/image_search/image_download.py
redditflow/image_search/image_search.py
redditflow/text_search/__init__.py
redditflow/text_search/classifier.py
redditflow/text_search/scraper.py
redditflow/text_search/search.py