Metadata-Version: 2.1
Name: redditflow
Version: 1.0.0
Summary: Data Curation over Time
Home-page: https://github.com/nfflow/redditflow
Author: Abhijith Neil Abraham
Author-email: abhijithneilabrahampk@gmail.com
License: MIT License
Platform: UNKNOWN
Requires-Python: >=3.6
License-File: LICENSE
